<annotation>
  <folder>IMG</folder>
  <filename>IMG_8765.jpg</filename>
  <source>
    <database>Unknown</database>
    <annotation>Unknown</annotation>
    <image>Unknown</image>
  </source>
  <size>
    <width>3024</width>
    <height>4032</height>
    <depth></depth>
  </size>
  <segmented>0</segmented>
  <object>
    <name>green_truck</name>
    <truncated>0</truncated>
    <occluded>0</occluded>
    <difficult>0</difficult>
    <bndbox>
      <xmin>245.15</xmin>
      <ymin>1609.1</ymin>
      <xmax>889.54</xmax>
      <ymax>3211.49</ymax>
    </bndbox>
    <attributes>
      <attribute>
        <name>rotation</name>
        <value>165.19999999999996</value>
      </attribute>
      <attribute>
        <name>track_id</name>
        <value>8</value>
      </attribute>
      <attribute>
        <name>keyframe</name>
        <value>True</value>
      </attribute>
    </attributes>
  </object>
  <object>
    <name>blue_truck</name>
    <truncated>0</truncated>
    <occluded>0</occluded>
    <difficult>0</difficult>
    <bndbox>
      <xmin>1291.5</xmin>
      <ymin>1736.91</ymin>
      <xmax>2700.11</xmax>
      <ymax>2382.61</ymax>
    </bndbox>
    <attributes>
      <attribute>
        <name>rotation</name>
        <value>64.90000000000003</value>
      </attribute>
      <attribute>
        <name>track_id</name>
        <value>9</value>
      </attribute>
      <attribute>
        <name>keyframe</name>
        <value>True</value>
      </attribute>
    </attributes>
  </object>
  <object>
    <name>red_truck</name>
    <truncated>0</truncated>
    <occluded>0</occluded>
    <difficult>0</difficult>
    <bndbox>
      <xmin>706.66</xmin>
      <ymin>1924.37</ymin>
      <xmax>2077.96</xmax>
      <ymax>2568.67</ymax>
    </bndbox>
    <attributes>
      <attribute>
        <name>rotation</name>
        <value>71.69999999999999</value>
      </attribute>
      <attribute>
        <name>track_id</name>
        <value>10</value>
      </attribute>
      <attribute>
        <name>keyframe</name>
        <value>True</value>
      </attribute>
    </attributes>
  </object>
</annotation>
