<annotation>
  <folder>IMG</folder>
  <filename>IMG_8746.jpg</filename>
  <source>
    <database>Unknown</database>
    <annotation>Unknown</annotation>
    <image>Unknown</image>
  </source>
  <size>
    <width>3024</width>
    <height>4032</height>
    <depth></depth>
  </size>
  <segmented>0</segmented>
  <object>
    <name>green_truck</name>
    <truncated>0</truncated>
    <occluded>0</occluded>
    <difficult>0</difficult>
    <bndbox>
      <xmin>136.5</xmin>
      <ymin>2209.77</ymin>
      <xmax>1694.16</xmax>
      <ymax>2933.17</ymax>
    </bndbox>
    <attributes>
      <attribute>
        <name>rotation</name>
        <value>310.2</value>
      </attribute>
      <attribute>
        <name>track_id</name>
        <value>8</value>
      </attribute>
      <attribute>
        <name>keyframe</name>
        <value>True</value>
      </attribute>
    </attributes>
  </object>
  <object>
    <name>blue_truck</name>
    <truncated>0</truncated>
    <occluded>0</occluded>
    <difficult>0</difficult>
    <bndbox>
      <xmin>1011.33</xmin>
      <ymin>1095.52</ymin>
      <xmax>1384.09</xmax>
      <ymax>1944.16</ymax>
    </bndbox>
    <attributes>
      <attribute>
        <name>rotation</name>
        <value>352.7</value>
      </attribute>
      <attribute>
        <name>track_id</name>
        <value>9</value>
      </attribute>
      <attribute>
        <name>keyframe</name>
        <value>True</value>
      </attribute>
    </attributes>
  </object>
  <object>
    <name>red_truck</name>
    <truncated>0</truncated>
    <occluded>0</occluded>
    <difficult>0</difficult>
    <bndbox>
      <xmin>1878.88</xmin>
      <ymin>1422.93</ymin>
      <xmax>2590.38</xmax>
      <ymax>2699.49</ymax>
    </bndbox>
    <attributes>
      <attribute>
        <name>rotation</name>
        <value>69.9</value>
      </attribute>
      <attribute>
        <name>track_id</name>
        <value>10</value>
      </attribute>
      <attribute>
        <name>keyframe</name>
        <value>True</value>
      </attribute>
    </attributes>
  </object>
</annotation>
